setup.py
funniest/__init__.py
fxh_funniest.egg-info/PKG-INFO
fxh_funniest.egg-info/SOURCES.txt
fxh_funniest.egg-info/dependency_links.txt
fxh_funniest.egg-info/not-zip-safe
fxh_funniest.egg-info/top_level.txt