Metadata-Version: 2.1
Name: fxh-funniest
Version: 0.1
Summary: The funniest joke in the world
Home-page: http://github.com/fp/funniest
Author: fangping
Author-email: huang.fp@gmail.com
License: MIT
Platform: UNKNOWN
